dacalc/calculator.py
dacalc-0.0.1.dist-info/WHEEL
dacalc-0.0.1.dist-info/METADATA
dacalc-0.0.1.dist-info/RECORD
