Metadata-Version: 2.1
Name: dacalc
Version: 0.0.1
Summary: A simple python calculator written by DA
Author: Damon Allison
Author-email: damon@damonallison.com
Requires-Python: >=3.9,<4.0
Classifier: Programming Language :: Python :: 3
Classifier: Programming Language :: Python :: 3.9
